ezmsg/vispy/__init__.py
ezmsg/vispy/frontends/__init__.py
ezmsg/vispy/frontends/main_window.py
ezmsg/vispy/helpers/__init__.py
ezmsg/vispy/helpers/axis_widgets.py
ezmsg/vispy/helpers/channel_magnification.py
ezmsg/vispy/helpers/constants.py
ezmsg/vispy/helpers/plot_configs.py
ezmsg/vispy/helpers/ranged_pan_zoom.py
ezmsg/vispy/helpers/types.py
ezmsg/vispy/units/__init__.py
ezmsg/vispy/units/application.py
ezmsg/vispy/units/complex_image_vis.py
ezmsg/vispy/units/histogram_vis.py
ezmsg/vispy/units/image_vis.py
ezmsg/vispy/units/line_vis.py
ezmsg/vispy/units/multi_line_vis.py
ezmsg/vispy/units/multitrace_vis.py
ezmsg/vispy/units/plot_vis.py
ezmsg/vispy/widgets/__init__.py
ezmsg/vispy/widgets/bar_plot_widget.py
ezmsg/vispy/widgets/base_plot_widget.py
ezmsg/vispy/widgets/complex_image_widget.py
ezmsg/vispy/widgets/histogram_widget.py
ezmsg/vispy/widgets/image_widget.py
ezmsg/vispy/widgets/line_plot_widget.py
ezmsg/vispy/widgets/line_widget.py
ezmsg/vispy/widgets/multi_line_widget.py
ezmsg/vispy/widgets/multitrace_widget.py
ezmsg/vispy/widgets/spectrogram_widget.py
ezmsg_vispy-0.3.4.dist-info/METADATA
ezmsg_vispy-0.3.4.dist-info/WHEEL
ezmsg_vispy-0.3.4.dist-info/licenses/LICENSE.txt
ezmsg_vispy-0.3.4.dist-info/RECORD
