Metadata-Version: 2.3
Name: ezmsg-vispy
Version: 0.3.4
License: Copyright (c) 2023 Johns Hopkins University Applied Physics Lab
License-File: LICENSE.txt
Requires-Python: >=3.9
Requires-Dist: ezmsg>=3.5.0
Requires-Dist: magicgui>=0.8.3
Requires-Dist: numpy>=1.26.4
Requires-Dist: pyopengl>=3.1.7
Requires-Dist: qdarkstyle>=3.2.3
Requires-Dist: qtpy>=2.4.1
Requires-Dist: vispy>=0.14.2
